teller/__init__.py
teller/explainer/__init__.py
teller/explainer/comparator.py
teller/explainer/conformalexplainer.py
teller/explainer/explainer.py
teller/fdaddiexplainer/__init__.py
teller/fdaddiexplainer/fdaddexplainer.py
teller/integratedgradients/__init__.py
teller/integratedgradients/integratedgradients.py
teller/nonconformist/__init__.py
teller/nonconformist/acp.py
teller/nonconformist/base.py
teller/nonconformist/cp.py
teller/nonconformist/evaluation.py
teller/nonconformist/icp.py
teller/nonconformist/nc.py
teller/nonconformist/util.py
teller/predictioninterval/__init__.py
teller/predictioninterval/predictioninterval.py
teller/utils/__init__.py
teller/utils/deepcopy.py
teller/utils/memoize.py
teller/utils/misc.py
teller/utils/numerical_gradient.py
teller/utils/numerical_gradient_conformal.py
teller/utils/numerical_gradient_gaussian.py
teller/utils/numerical_gradient_jackknife.py
teller/utils/numerical_interactions_gaussian.py
teller/utils/numerical_interactions_jackknife.py
teller/utils/progress_bar.py
teller/utils/scoring.py
teller/utils/t_test.py
teller/utils/var_test.py
the_teller-0.13.0.dist-info/licenses/LICENSE
the_teller-0.13.0.dist-info/METADATA
the_teller-0.13.0.dist-info/WHEEL
the_teller-0.13.0.dist-info/top_level.txt
the_teller-0.13.0.dist-info/RECORD
