Metadata-Version: 2.4
Name: the-teller
Version: 0.13.0
Summary: teller, explainable machine learning
Home-page: https://github.com/thierrymoudiki/teller
Download-URL: https://github.com/thierrymoudiki/teller/tarball/0.13.0
Author: T. Moudiki
Author-email: thierry.moudiki@gmail.com
License: BSD
Classifier: Development Status :: 3 - Alpha
Classifier: Intended Audience :: Developers
Classifier: Programming Language :: Python :: 3
License-File: LICENSE
Requires-Dist: joblib
Requires-Dist: nnetsauce
Requires-Dist: numpy
Requires-Dist: pandas
Requires-Dist: seaborn
Requires-Dist: scikit-learn
Requires-Dist: scipy
Requires-Dist: tqdm
Dynamic: author
Dynamic: author-email
Dynamic: classifier
Dynamic: description
Dynamic: download-url
Dynamic: home-page
Dynamic: keywords
Dynamic: license
Dynamic: license-file
Dynamic: requires-dist
Dynamic: summary
